elasticsearch9/__init__.py
elasticsearch9/_otel.py
elasticsearch9/_utils.py
elasticsearch9/_version.py
elasticsearch9/client.py
elasticsearch9/compat.py
elasticsearch9/exceptions.py
elasticsearch9/py.typed
elasticsearch9/serializer.py
elasticsearch9/_async/__init__.py
elasticsearch9/_async/helpers.py
elasticsearch9/_async/client/__init__.py
elasticsearch9/_async/client/_base.py
elasticsearch9/_async/client/async_search.py
elasticsearch9/_async/client/autoscaling.py
elasticsearch9/_async/client/cat.py
elasticsearch9/_async/client/ccr.py
elasticsearch9/_async/client/cluster.py
elasticsearch9/_async/client/connector.py
elasticsearch9/_async/client/dangling_indices.py
elasticsearch9/_async/client/enrich.py
elasticsearch9/_async/client/eql.py
elasticsearch9/_async/client/esql.py
elasticsearch9/_async/client/features.py
elasticsearch9/_async/client/fleet.py
elasticsearch9/_async/client/graph.py
elasticsearch9/_async/client/ilm.py
elasticsearch9/_async/client/indices.py
elasticsearch9/_async/client/inference.py
elasticsearch9/_async/client/ingest.py
elasticsearch9/_async/client/license.py
elasticsearch9/_async/client/logstash.py
elasticsearch9/_async/client/migration.py
elasticsearch9/_async/client/ml.py
elasticsearch9/_async/client/monitoring.py
elasticsearch9/_async/client/nodes.py
elasticsearch9/_async/client/query_rules.py
elasticsearch9/_async/client/rollup.py
elasticsearch9/_async/client/search_application.py
elasticsearch9/_async/client/searchable_snapshots.py
elasticsearch9/_async/client/security.py
elasticsearch9/_async/client/shutdown.py
elasticsearch9/_async/client/simulate.py
elasticsearch9/_async/client/slm.py
elasticsearch9/_async/client/snapshot.py
elasticsearch9/_async/client/sql.py
elasticsearch9/_async/client/ssl.py
elasticsearch9/_async/client/streams.py
elasticsearch9/_async/client/synonyms.py
elasticsearch9/_async/client/tasks.py
elasticsearch9/_async/client/text_structure.py
elasticsearch9/_async/client/transform.py
elasticsearch9-9.1.3.dist-info/METADATA
elasticsearch9-9.1.3.dist-info/WHEEL
elasticsearch9-9.1.3.dist-info/licenses/LICENSE
elasticsearch9-9.1.3.dist-info/licenses/NOTICE
elasticsearch9-9.1.3.dist-info/RECORD
