Metadata-Version: 2.4
Name: elasticsearch9
Version: 9.1.3
Summary: Python client for Elasticsearch
Project-URL: Documentation, https://elasticsearch9-py.readthedocs.io/
Project-URL: Homepage, https://github.com/elastic/elasticsearch9-py
Project-URL: Issue Tracker, https://github.com/elastic/elasticsearch9-py/issues
Project-URL: Source Code, https://github.com/elastic/elasticsearch9-py
Author-email: Elastic Client Library Maintainers <client-libs@elastic.co>
Maintainer-email: Elastic Client Library Maintainers <client-libs@elastic.co>
License-Expression: Apache-2.0
License-File: LICENSE
License-File: NOTICE
Keywords: REST,client,elastic,elasticsearch9,index,kibana,mapping,search
Classifier: Development Status :: 5 - Production/Stable
Classifier: Intended Audience :: Developers
Classifier: License :: OSI Approved :: Apache Software License
Classifier: Operating System :: OS Independent
Classifier: Programming Language :: Python
Classifier: Programming Language :: Python :: 3
Classifier: Programming Language :: Python :: 3.9
Classifier: Programming Language :: Python :: 3.10
Classifier: Programming Language :: Python :: 3.11
Classifier: Programming Language :: Python :: 3.12
Classifier: Programming Language :: Python :: 3.13
Classifier: Programming Language :: Python :: Implementation :: CPython
Classifier: Programming Language :: Python :: Implementation :: PyPy
Requires-Python: >=3.9
Requires-Dist: elastic-transport<10,>=9.1.0
Requires-Dist: python-dateutil
Requires-Dist: typing-extensions
Provides-Extra: async
Requires-Dist: aiohttp<4,>=3; extra == 'async'
Provides-Extra: dev
Requires-Dist: aiohttp; extra == 'dev'
Requires-Dist: black; extra == 'dev'
Requires-Dist: build; extra == 'dev'
Requires-Dist: coverage; extra == 'dev'
Requires-Dist: isort; extra == 'dev'
Requires-Dist: jinja2; extra == 'dev'
Requires-Dist: mapbox-vector-tile; extra == 'dev'
Requires-Dist: mypy; extra == 'dev'
Requires-Dist: nox; extra == 'dev'
Requires-Dist: numpy; extra == 'dev'
Requires-Dist: orjson; extra == 'dev'
Requires-Dist: pandas; extra == 'dev'
Requires-Dist: pyarrow; (python_version < '3.14') and extra == 'dev'
Requires-Dist: pyright; extra == 'dev'
Requires-Dist: pytest; extra == 'dev'
Requires-Dist: pytest-asyncio; extra == 'dev'
Requires-Dist: pytest-cov; extra == 'dev'
Requires-Dist: pytest-mock; extra == 'dev'
Requires-Dist: python-dateutil; extra == 'dev'
Requires-Dist: pyyaml>=5.4; extra == 'dev'
Requires-Dist: requests<3,>=2; extra == 'dev'
Requires-Dist: simsimd; extra == 'dev'
Requires-Dist: tqdm; extra == 'dev'
Requires-Dist: twine; extra == 'dev'
Requires-Dist: types-python-dateutil; extra == 'dev'
Requires-Dist: types-tqdm; extra == 'dev'
Requires-Dist: unasync; extra == 'dev'
Provides-Extra: docs
Requires-Dist: sphinx; extra == 'docs'
Requires-Dist: sphinx-autodoc-typehints; extra == 'docs'
Requires-Dist: sphinx-rtd-theme>=2.0; extra == 'docs'
Provides-Extra: orjson
Requires-Dist: orjson>=3; extra == 'orjson'
Provides-Extra: pyarrow
Requires-Dist: pyarrow>=1; extra == 'pyarrow'
Provides-Extra: requests
Requires-Dist: requests!=2.32.2,<3.0.0,>=2.4.0; extra == 'requests'
Provides-Extra: vectorstore-mmr
Requires-Dist: numpy>=1; extra == 'vectorstore-mmr'
Requires-Dist: simsimd>=3; extra == 'vectorstore-mmr'
